drfpasswordlesskvn/__init__.py
drfpasswordlesskvn/__version__.py
drfpasswordlesskvn/admin.py
drfpasswordlesskvn/apps.py
drfpasswordlesskvn/models.py
drfpasswordlesskvn/serializers.py
drfpasswordlesskvn/services.py
drfpasswordlesskvn/settings.py
drfpasswordlesskvn/signals.py
drfpasswordlesskvn/urls.py
drfpasswordlesskvn/utils.py
drfpasswordlesskvn/views.py
drfpasswordlesskvn/migrations/0001_initial.py
drfpasswordlesskvn/migrations/0002_auto_20200122_0424.py
drfpasswordlesskvn/migrations/0003_callbacktoken_type.py
drfpasswordlesskvn/migrations/0004_auto_20200125_0853.py
drfpasswordlesskvn/migrations/0005_auto_20201117_0410.py
drfpasswordlesskvn/migrations/0006_authenticatableuser.py
drfpasswordlesskvn/migrations/0007_rename_authenticatableuser_mobile.py
drfpasswordlesskvn/migrations/0008_alter_mobile_mobile.py
drfpasswordlesskvn/migrations/0009_alter_mobile_mobile.py
drfpasswordlesskvn/migrations/__init__.py
drfpasswordlesskvn/templates/passwordless_default_token_email.html
drfpasswordlesskvn/templates/passwordless_default_verification_token_email.html
drfpasswordlesskvn-1.5.8.dist-info/LICENSE
drfpasswordlesskvn-1.5.8.dist-info/METADATA
drfpasswordlesskvn-1.5.8.dist-info/WHEEL
drfpasswordlesskvn-1.5.8.dist-info/top_level.txt
drfpasswordlesskvn-1.5.8.dist-info/RECORD
