Metadata-Version: 2.1
Name: drfpasswordlesskvn
Version: 1.5.8
Summary: Passwordless auth for Django Rest Framework Token Authentication using Kavenegar.
Home-page: https://github.com/aramhuseiny/django-rest-framework-passwordless-kvn
Author: Hedi
Author-email: huseiny.aram@gmail.com
License: MIT
Platform: UNKNOWN
Classifier: License :: OSI Approved :: MIT License
Classifier: Programming Language :: Python
Classifier: Programming Language :: Python :: 3
Classifier: Programming Language :: Python :: 3.6
Classifier: Programming Language :: Python :: Implementation :: CPython
Classifier: Programming Language :: Python :: Implementation :: PyPy
Classifier: Development Status :: 5 - Production/Stable
Classifier: Environment :: Web Environment
Classifier: Framework :: Django
Classifier: Intended Audience :: Developers
Classifier: Operating System :: OS Independent
Classifier: Programming Language :: Python
Classifier: Topic :: Internet :: WWW/HTTP
Requires-Python: >=3
License-File: LICENSE
Requires-Dist: Django
Requires-Dist: djangorestframework
Requires-Dist: kavenegar
